<?xml version="1.0" encoding="ISO-8859-1"?>
<recipe>

<!--
<command_sequence>
  <loop name = "Regbead1" increment = "name">	
  <item name = "Regbead1"></item>
  </loop>
</command_sequence>

<item name = "Regbead1">
  <movie>
    <name increment = "Yes">Regbead_1</name>
    <length>120</length>
    <lock_target>-400.0</lock_target>
    <find_sum>1.0</find_sum>
    <parameters>1</parameters>
    <delay>2000</delay>
    <progression><type>lockedout</type></progression>
    <variable_entry name = "Regbead1"></variable_entry>
  </movie>
</item>

<loop_variable name = "Regbead1">
   <file_path>bead_field_1.txt</file_path>
</loop_variable>

-->
<command_sequence>
  <loop name = "Conv" increment = "name">	
  	<item name = "Conv"></item>
  </loop>
</command_sequence>

<item name = "Conv">
  <movie>
    <name increment = "Yes">Conv</name>
    <length>12</length>
    <lock_target>0.0</lock_target>
    <find_sum>1.0</find_sum>
    <parameters>2</parameters>
    <delay>2000</delay>
    <progression><type>lockedout</type></progression>
    <variable_entry name = "Conv"></variable_entry>
  </movie>
</item>

<loop_variable name = "Conv">
   <file_path>positions.txt</file_path>
</loop_variable>
<!--

<command_sequence>
  <loop name = "FFC" increment = "name">	
  <item name = "FFC"></item>
  </loop>
</command_sequence>

<item name = "FFC">
  <movie>
    <name increment = "Yes">FFC</name>
    <length>80</length>
    <lock_target>500.0</lock_target>
   <find_sum>1.0</find_sum>
    <parameters>3</parameters>
    <delay>2000</delay>
    <progression><type>lockedout</type></progression>
    <variable_entry name = "FFC"></variable_entry>
  </movie>
</item>

<loop_variable name = "FFC">
   <file_path>FFC_bead_field.txt</file_path>
</loop_variable>


<command_sequence>
  <loop name = "Regbead2" increment = "name">	
  <item name = "Regbead2"></item>
  </loop>
</command_sequence>

<item name = "Regbead2">
  <movie>
    <name increment = "Yes">Regbead_2</name>
    <length>120</length>
    <lock_target>-400.0</lock_target>
    <find_sum>1.0</find_sum>
    <parameters>1</parameters>
    <delay>2000</delay>
    <progression><type>lockedout</type></progression>
    <variable_entry name = "Regbead2"></variable_entry>
  </movie>
</item>

<loop_variable name = "Regbead2">
   <file_path>bead_field_2.txt</file_path>
</loop_variable>

-->

<command_sequence>
  <loop name = "storm" increment = "name">	
  	<item name = "750storm"></item>
	<item name = "647storm"></item>
  </loop>
</command_sequence>

<item name = "750storm">
  <movie>
    <name increment = "Yes">750storm</name>
    <length>8000</length>
    <lock_target>-800.0</lock_target>
    <find_sum>1.0</find_sum>
    <parameters>4</parameters>
    <delay>2000</delay>
    <progression><type>file</type>
    <filename>C:\Users\Sperry3\acquisition\create_xml\powertest\750storm_0001.power</filename>
    </progression>
    <variable_entry name = "storm"></variable_entry>
    <min_spots>0</min_spots>
  </movie>
</item>

<item name = "647storm">
  <movie>
    <name increment = "Yes">647storm</name>
    <length>8000</length>
    <lock_target>-500.0</lock_target>
    <find_sum>1.0</find_sum>
    <parameters>5</parameters>
    <delay>2000</delay>
    <progression><type>file</type>
    <filename>C:\Users\Sperry3\acquisition\create_xml\powertest\647storm_0001.power</filename>
    </progression>
    <variable_entry name = "storm"></variable_entry>
    <min_spots>10</min_spots>
  </movie>
</item>



<loop_variable name = "storm">
   <file_path>positions.txt</file_path>
</loop_variable>


<command_sequence>
  <loop name = "storm" increment = "name">	
  	<item name = "561storm"></item>

  </loop>
</command_sequence>

<item name = "561storm">
  <movie>
    <name increment = "Yes">561storm</name>
    <length>8000</length>
    <lock_target>-50.0</lock_target>
    <find_sum>1.0</find_sum>
    <parameters>6</parameters>
    <delay>2000</delay>
    <progression><type>file</type>
    <filename>C:\Users\Sperry3\acquisition\create_xml\powertest\561storm_0001.power</filename>
    </progression>
    <variable_entry name = "storm"></variable_entry>
    <min_spots>0</min_spots>
  </movie>
</item>

<!--
	<item name = "488storm"></item>
<item name = "488storm">
  <movie>
    <name increment = "Yes">488storm</name>
    <length>9000</length>
    <lock_target>-300.0</lock_target>
    <find_sum>1.0</find_sum>
    <parameters>7</parameters>
    <delay>2000</delay>
    <progression><type>file</type>
    <filename>C:\Users\Sperry3\acquisition\create_xml\powertest\488storm_0001.power</filename>
    </progression>
    <variable_entry name = "storm"></variable_entry>
    <min_spots>0</min_spots>
  </movie>
</item>
-->

<loop_variable name = "storm">
   <file_path>positions.txt</file_path>
</loop_variable>

</recipe>

